journalmk/__init__.py
journalmk/__main__.py
journalmk/journalmk.py
journalmk-2023.1.1.dist-info/LICENSE
journalmk-2023.1.1.dist-info/METADATA
journalmk-2023.1.1.dist-info/WHEEL
journalmk-2023.1.1.dist-info/entry_points.txt
journalmk-2023.1.1.dist-info/top_level.txt
journalmk-2023.1.1.dist-info/RECORD
