Metadata-Version: 2.1
Name: journalmk
Version: 2023.1.1
Summary: Creates a pdf notebook/journal out of your digital notes, using latex + python
Home-page: https://github.com/riemarc/journalmk
Author: Marcus Riesmeier
Author-email: gluehen-sierren-0c@icloud.com
License: BSD 3-Clause License
Classifier: Programming Language :: Python :: 3
Classifier: License :: OSI Approved :: BSD License
Classifier: Operating System :: OS Independent
License-File: LICENSE
